belltower/__init__.py
belltower/bell.py
belltower/bell_type.py
belltower/call.py
belltower/page_parsing.py
belltower/ringing_room.py
belltower/stroke.py
belltower-0.1.0.dist-info/LICENSE
belltower-0.1.0.dist-info/METADATA
belltower-0.1.0.dist-info/WHEEL
belltower-0.1.0.dist-info/top_level.txt
belltower-0.1.0.dist-info/RECORD
