Metadata-Version: 2.1
Name: belltower
Version: 0.1.0
Summary: A Pythonic interface to Ringing Room, an online change ringing platform.
Home-page: https://github.com/kneasle/belltower
Author: Ben White-Horne
Author-email: kneasle@gmail.com
License: MIT
Platform: any
Classifier: Programming Language :: Python :: 3
Classifier: License :: OSI Approved :: MIT License
Classifier: Operating System :: OS Independent
Requires-Python: >=3.6
Requires-Dist: python-engineio (<4)
Requires-Dist: python-socketio (<5)
Requires-Dist: requests
Requires-Dist: websocket-client
